gradle.properties
hexdoc_hex_ars_link/__gradle_version__.py
hexdoc_hex_ars_link/__init__.py
hexdoc_hex_ars_link/__version__.py
hexdoc_hex_ars_link/_hooks.py
hexdoc_hex_ars_link/py.typed
hexdoc_hex_ars_link/_export/.gitignore
hexdoc_hex_ars_link/_export/__init__.py
hexdoc_hex_ars_link/_export/generated/__init__.py
hexdoc_hex_ars_link/_export/generated/hex_ars_link.hexdoc.json
hexdoc_hex_ars_link/_export/generated/hex_ars_link.patterns.hexdoc.json
hexdoc_hex_ars_link/_export/generated/assets/hex_ars_link/lang/en_us.flatten.json5
hexdoc_hex_ars_link/_export/generated/assets/hex_ars_link/lang/en_us.json
hexdoc_hex_ars_link/_export/generated/assets/hex_ars_link/lang/zh_cn.json
hexdoc_hex_ars_link/_export/generated/assets/hex_ars_link/models/item/hex_callback.json
hexdoc_hex_ars_link/_export/generated/assets/hex_ars_link/models/item/linker_advanced.json
hexdoc_hex_ars_link/_export/generated/assets/hex_ars_link/models/item/linker_base.json
hexdoc_hex_ars_link/_export/generated/assets/hex_ars_link/models/item/linker_great.json
hexdoc_hex_ars_link/_export/generated/assets/hex_ars_link/textures/item/hex_callback.png
hexdoc_hex_ars_link/_export/generated/assets/hex_ars_link/textures/item/linker_advanced.png
hexdoc_hex_ars_link/_export/generated/assets/hex_ars_link/textures/item/linker_base.png
hexdoc_hex_ars_link/_export/generated/assets/hex_ars_link/textures/item/linker_great.png
hexdoc_hex_ars_link/_export/generated/assets/hexcasting/patchouli_books/thehexbook/en_us/entries/glyph_patterns.json
hexdoc_hex_ars_link/_export/generated/assets/hexcasting/patchouli_books/thehexbook/en_us/entries/linkers.json
hexdoc_hex_ars_link/_export/generated/data/hexcasting/tags/action/per_world_pattern.json
hexdoc_hex_ars_link/_templates/__init__.py
hexdoc_hex_ars_link-0.9.2.4.1.0.1.dist-info/METADATA
hexdoc_hex_ars_link-0.9.2.4.1.0.1.dist-info/WHEEL
hexdoc_hex_ars_link-0.9.2.4.1.0.1.dist-info/entry_points.txt
hexdoc_hex_ars_link-0.9.2.4.1.0.1.dist-info/RECORD
