Metadata-Version: 2.4
Name: hexdoc-hex-ars-link
Version: 0.9.2.4.1.0.1
Summary: Python web book docgen and hexdoc plugin for Hex-Ars Linker.
Project-URL: Homepage, https://yukkuric.github.io/HexArsLinker/
Project-URL: Source, https://github.com/YukkuriC/HexArsLinker
Author: YukkuriC
Keywords: hexdoc
Requires-Python: >=3.11
Requires-Dist: hexdoc-hexcasting~=0.11.2.1.0
Provides-Extra: dev
Requires-Dist: ruff~=0.11.2; extra == 'dev'
